ix_rest_tools/__init__.py
ix_rest_tools/examples.py
ix_rest_tools/ix_rest_tools.py
ix_rest_tools-0.1.3.dist-info/METADATA
ix_rest_tools-0.1.3.dist-info/WHEEL
ix_rest_tools-0.1.3.dist-info/top_level.txt
ix_rest_tools-0.1.3.dist-info/RECORD
